fosslight_oss_pkg/__init__.py
fosslight_oss_pkg/_convert.py
fosslight_oss_pkg/_parsing_excel.py
fosslight_prechecker/__init__.py
fosslight_prechecker/_add.py
fosslight_prechecker/_add_header.py
fosslight_prechecker/_constant.py
fosslight_prechecker/_download_lic.py
fosslight_prechecker/_help.py
fosslight_prechecker/_precheck.py
fosslight_prechecker/_result.py
fosslight_prechecker/_result_html.py
fosslight_prechecker/cli.py
fosslight_prechecker/LICENSES/LICENSE
fosslight_prechecker/LICENSES/LicenseRef-3rd_party_licenses.txt
fosslight_prechecker/templates/default_template.jinja2
fosslight_prechecker/templates/default_template.jinja2.license
fosslight_prechecker-4.0.3.dist-info/LICENSE
fosslight_prechecker-4.0.3.dist-info/METADATA
fosslight_prechecker-4.0.3.dist-info/WHEEL
fosslight_prechecker-4.0.3.dist-info/entry_points.txt
fosslight_prechecker-4.0.3.dist-info/top_level.txt
fosslight_prechecker-4.0.3.dist-info/RECORD
