Metadata-Version: 2.1
Name: fosslight-prechecker
Version: 4.0.3
Summary: FOSSLight Prechecker
Home-page: https://github.com/fosslight/fosslight_prechecker
Author: LG Electronics
License: GPL-3.0-only
Download-URL: https://github.com/fosslight/fosslight_prechecker
Platform: UNKNOWN
Classifier: License :: OSI Approved :: GNU General Public License v3 (GPLv3)
Classifier: Programming Language :: Python :: 3
Classifier: Programming Language :: Python :: 3.6
Classifier: Programming Language :: Python :: 3.7
Classifier: Programming Language :: Python :: 3.8
Classifier: Programming Language :: Python :: 3.9
Requires-Dist: python-debian==0.1.40
Requires-Dist: binaryornot
Requires-Dist: requests
Requires-Dist: reuse==1.1.2
Requires-Dist: PyYAML
Requires-Dist: fosslight-util>=2.1.10
Requires-Dist: jinja2
Requires-Dist: pyaskalono
